.gitignore
.travis.yml
MANIFEST.in
README.rst
bootstrap.py
buildout.cfg
setup.cfg
setup.py
travis-4.1.x.cfg
travis-4.2.x.cfg
travis-4.3.x.cfg
travis.cfg
docs/HISTORY.txt
docs/INSTALL.txt
docs/LICENSE.GPL
docs/LICENSE.txt
src/theming/__init__.py
src/theming.toolkit.viewlets.egg-info/PKG-INFO
src/theming.toolkit.viewlets.egg-info/SOURCES.txt
src/theming.toolkit.viewlets.egg-info/dependency_links.txt
src/theming.toolkit.viewlets.egg-info/entry_points.txt
src/theming.toolkit.viewlets.egg-info/namespace_packages.txt
src/theming.toolkit.viewlets.egg-info/not-zip-safe
src/theming.toolkit.viewlets.egg-info/requires.txt
src/theming.toolkit.viewlets.egg-info/top_level.txt
src/theming/toolkit/__init__.py
src/theming/toolkit/viewlets/__init__.py
src/theming/toolkit/viewlets/configure.zcml
src/theming/toolkit/viewlets/i18n.py
src/theming/toolkit/viewlets/testing.py
src/theming/toolkit/viewlets/browser/__init__.py
src/theming/toolkit/viewlets/browser/collection_viewlets.py
src/theming/toolkit/viewlets/browser/configure.zcml
src/theming/toolkit/viewlets/browser/header_plugins.py
src/theming/toolkit/viewlets/browser/interfaces.py
src/theming/toolkit/viewlets/browser/viewlets.py
src/theming/toolkit/viewlets/browser/templates/carousel_viewlet.pt
src/theming/toolkit/viewlets/browser/templates/featured-navigation.pt
src/theming/toolkit/viewlets/browser/templates/header_plugins.pt
src/theming/toolkit/viewlets/browser/templates/socialheader.pt
src/theming/toolkit/viewlets/browser/templates/titlecontact.pt
src/theming/toolkit/viewlets/profiles/default/actions.xml
src/theming/toolkit/viewlets/profiles/default/browserlayer.xml
src/theming/toolkit/viewlets/profiles/default/metadata.xml
src/theming/toolkit/viewlets/tests/__init__.py
src/theming/toolkit/viewlets/tests/test_setup.py
src/theming/toolkit/viewlets/tests/test_viewlets.py