Metadata-Version: 1.0
Name: theming.toolkit.viewlets
Version: 0.1
Summary: A product that allows to activate a set of viewlets for Plone content items.
Home-page: http://propertyshelf.com
Author: Jens Krause
Author-email: jens@propertyshelf.com
License: GPL
Platform: UNKNOWN
Classifier: Framework :: Plone
Classifier: Programming Language :: Python
